[{"name": "tabular_bench.BenchmarkTabular.peakmem_BoostingOverfit", "idx": 0, "pretty_name": "tabular_bench.BenchmarkTabular.peakmem_BoostingOverfit('lending_club')", "last_rev": 1221, "last_value": 369659904.0, "last_err": 0.0, "prev_value": null, "change_rev": null}, {"name": "tabular_bench.BenchmarkTabular.peakmem_BoostingOverfit", "idx": 1, "pretty_name": "tabular_bench.BenchmarkTabular.peakmem_BoostingOverfit('avocado')", "last_rev": 1221, "last_value": 355926016.0, "last_err": 0.0, "prev_value": null, "change_rev": null}, {"name": "tabular_bench.BenchmarkTabular.peakmem_CalibrationScore", "idx": 0, "pretty_name": "tabular_bench.BenchmarkTabular.peakmem_CalibrationScore('lending_club')", "last_rev": 1221, "last_value": 368418816.0, "last_err": 0.0, "prev_value": null, "change_rev": null}, {"name": "tabular_bench.BenchmarkTabular.peakmem_CalibrationScore", "idx": 1, "pretty_name": "tabular_bench.BenchmarkTabular.peakmem_CalibrationScore('avocado')", "last_rev": 1221, "last_value": 354344960.0, "last_err": 0.0, "prev_value": null, "change_rev": null}, {"name": "tabular_bench.BenchmarkTabular.peakmem_CategoryMismatchTrainTest", "idx": 0, "pretty_name": "tabular_bench.BenchmarkTabular.peakmem_CategoryMismatchTrainTest('lending_club')", "last_rev": 1221, "last_value": 362360832.0, "last_err": 0.0, "prev_value": null, "change_rev": null}, {"name": "tabular_bench.BenchmarkTabular.peakmem_CategoryMismatchTrainTest", "idx": 1, "pretty_name": "tabular_bench.BenchmarkTabular.peakmem_CategoryMismatchTrainTest('avocado')", "last_rev": 1221, "last_value": 355753984.0, "last_err": 0.0, "prev_value": null, "change_rev": null}, {"name": "tabular_bench.BenchmarkTabular.peakmem_ClassImbalance", "idx": 0, "pretty_name": "tabular_bench.BenchmarkTabular.peakmem_ClassImbalance('lending_club')", "last_rev": 1221, "last_value": 364318720.0, "last_err": 0.0, "prev_value": null, "change_rev": null}, {"name": "tabular_bench.BenchmarkTabular.peakmem_ClassImbalance", "idx": 1, "pretty_name": "tabular_bench.BenchmarkTabular.peakmem_ClassImbalance('avocado')", "last_rev": 1221, "last_value": 347107328.0, "last_err": 0.0, "prev_value": null, "change_rev": null}, {"name": "tabular_bench.BenchmarkTabular.peakmem_ColumnsInfo", "idx": 0, "pretty_name": "tabular_bench.BenchmarkTabular.peakmem_ColumnsInfo('lending_club')", "last_rev": 1221, "last_value": 348831744.0, "last_err": 0.0, "prev_value": null, "change_rev": null}, {"name": "tabular_bench.BenchmarkTabular.peakmem_ColumnsInfo", "idx": 1, "pretty_name": "tabular_bench.BenchmarkTabular.peakmem_ColumnsInfo('avocado')", "last_rev": 1221, "last_value": 348831744.0, "last_err": 0.0, "prev_value": null, "change_rev": null}, {"name": "tabular_bench.BenchmarkTabular.peakmem_ConflictingLabels", "idx": 0, "pretty_name": "tabular_bench.BenchmarkTabular.peakmem_ConflictingLabels('lending_club')", "last_rev": 1221, "last_value": 394465280.0, "last_err": 0.0, "prev_value": null, "change_rev": null}, {"name": "tabular_bench.BenchmarkTabular.peakmem_ConflictingLabels", "idx": 1, "pretty_name": "tabular_bench.BenchmarkTabular.peakmem_ConflictingLabels('avocado')", "last_rev": 1221, "last_value": 347107328.0, "last_err": 0.0, "prev_value": null, "change_rev": null}, {"name": "tabular_bench.BenchmarkTabular.peakmem_ConfusionMatrixReport", "idx": 0, "pretty_name": "tabular_bench.BenchmarkTabular.peakmem_ConfusionMatrixReport('lending_club')", "last_rev": 1221, "last_value": 368508928.0, "last_err": 0.0, "prev_value": null, "change_rev": null}, {"name": "tabular_bench.BenchmarkTabular.peakmem_ConfusionMatrixReport", "idx": 1, "pretty_name": "tabular_bench.BenchmarkTabular.peakmem_ConfusionMatrixReport('avocado')", "last_rev": 1221, "last_value": 354344960.0, "last_err": 0.0, "prev_value": null, "change_rev": null}, {"name": "tabular_bench.BenchmarkTabular.peakmem_DataDuplicates", "idx": 0, "pretty_name": "tabular_bench.BenchmarkTabular.peakmem_DataDuplicates('lending_club')", "last_rev": 1221, "last_value": 366374912.0, "last_err": 0.0, "prev_value": null, "change_rev": null}, {"name": "tabular_bench.BenchmarkTabular.peakmem_DataDuplicates", "idx": 1, "pretty_name": "tabular_bench.BenchmarkTabular.peakmem_DataDuplicates('avocado')", "last_rev": 1221, "last_value": 358391808.0, "last_err": 0.0, "prev_value": null, "change_rev": null}, {"name": "tabular_bench.BenchmarkTabular.peakmem_DatasetsSizeComparison", "idx": 0, "pretty_name": "tabular_bench.BenchmarkTabular.peakmem_DatasetsSizeComparison('lending_club')", "last_rev": 1221, "last_value": 347574272.0, "last_err": 0.0, "prev_value": null, "change_rev": null}, {"name": "tabular_bench.BenchmarkTabular.peakmem_DatasetsSizeComparison", "idx": 1, "pretty_name": "tabular_bench.BenchmarkTabular.peakmem_DatasetsSizeComparison('avocado')", "last_rev": 1221, "last_value": 347574272.0, "last_err": 0.0, "prev_value": null, "change_rev": null}, {"name": "tabular_bench.BenchmarkTabular.peakmem_DateTrainTestLeakageDuplicates", "idx": 0, "pretty_name": "tabular_bench.BenchmarkTabular.peakmem_DateTrainTestLeakageDuplicates('lending_club')", "last_rev": 1221, "last_value": 361762816.0, "last_err": 0.0, "prev_value": null, "change_rev": null}, {"name": "tabular_bench.BenchmarkTabular.peakmem_DateTrainTestLeakageDuplicates", "idx": 1, "pretty_name": "tabular_bench.BenchmarkTabular.peakmem_DateTrainTestLeakageDuplicates('avocado')", "last_rev": 1221, "last_value": 355483648.0, "last_err": 0.0, "prev_value": null, "change_rev": null}, {"name": "tabular_bench.BenchmarkTabular.peakmem_DateTrainTestLeakageOverlap", "idx": 0, "pretty_name": "tabular_bench.BenchmarkTabular.peakmem_DateTrainTestLeakageOverlap('lending_club')", "last_rev": 1221, "last_value": 361762816.0, "last_err": 0.0, "prev_value": null, "change_rev": null}, {"name": "tabular_bench.BenchmarkTabular.peakmem_DateTrainTestLeakageOverlap", "idx": 1, "pretty_name": "tabular_bench.BenchmarkTabular.peakmem_DateTrainTestLeakageOverlap('avocado')", "last_rev": 1221, "last_value": 355483648.0, "last_err": 0.0, "prev_value": null, "change_rev": null}, {"name": "tabular_bench.BenchmarkTabular.peakmem_FeatureFeatureCorrelation", "idx": 0, "pretty_name": "tabular_bench.BenchmarkTabular.peakmem_FeatureFeatureCorrelation('lending_club')", "last_rev": 1221, "last_value": 370429952.0, "last_err": 0.0, "prev_value": null, "change_rev": null}, {"name": "tabular_bench.BenchmarkTabular.peakmem_FeatureFeatureCorrelation", "idx": 1, "pretty_name": "tabular_bench.BenchmarkTabular.peakmem_FeatureFeatureCorrelation('avocado')", "last_rev": 1221, "last_value": 368885760.0, "last_err": 0.0, "prev_value": null, "change_rev": null}, {"name": "tabular_bench.BenchmarkTabular.peakmem_FeatureLabelCorrelation", "idx": 0, "pretty_name": "tabular_bench.BenchmarkTabular.peakmem_FeatureLabelCorrelation('lending_club')", "last_rev": 1221, "last_value": 363520000.0, "last_err": 0.0, "prev_value": null, "change_rev": null}, {"name": "tabular_bench.BenchmarkTabular.peakmem_FeatureLabelCorrelation", "idx": 1, "pretty_name": "tabular_bench.BenchmarkTabular.peakmem_FeatureLabelCorrelation('avocado')", "last_rev": 1221, "last_value": 357855232.0, "last_err": 0.0, "prev_value": null, "change_rev": null}, {"name": "tabular_bench.BenchmarkTabular.peakmem_FeatureLabelCorrelationChange", "idx": 0, "pretty_name": "tabular_bench.BenchmarkTabular.peakmem_FeatureLabelCorrelationChange('lending_club')", "last_rev": 1221, "last_value": 364146688.0, "last_err": 0.0, "prev_value": null, "change_rev": null}, {"name": "tabular_bench.BenchmarkTabular.peakmem_FeatureLabelCorrelationChange", "idx": 1, "pretty_name": "tabular_bench.BenchmarkTabular.peakmem_FeatureLabelCorrelationChange('avocado')", "last_rev": 1221, "last_value": 358895616.0, "last_err": 0.0, "prev_value": null, "change_rev": null}, {"name": "tabular_bench.BenchmarkTabular.peakmem_IdentifierLabelCorrelation", "idx": 0, "pretty_name": "tabular_bench.BenchmarkTabular.peakmem_IdentifierLabelCorrelation('lending_club')", "last_rev": 1221, "last_value": 372244480.0, "last_err": 0.0, "prev_value": null, "change_rev": null}, {"name": "tabular_bench.BenchmarkTabular.peakmem_IdentifierLabelCorrelation", "idx": 1, "pretty_name": "tabular_bench.BenchmarkTabular.peakmem_IdentifierLabelCorrelation('avocado')", "last_rev": 1221, "last_value": 370122752.0, "last_err": 0.0, "prev_value": null, "change_rev": null}, {"name": "tabular_bench.BenchmarkTabular.peakmem_IndexTrainTestLeakage", "idx": 0, "pretty_name": "tabular_bench.BenchmarkTabular.peakmem_IndexTrainTestLeakage('lending_club')", "last_rev": 1221, "last_value": 360439808.0, "last_err": 0.0, "prev_value": null, "change_rev": null}, {"name": "tabular_bench.BenchmarkTabular.peakmem_IndexTrainTestLeakage", "idx": 1, "pretty_name": "tabular_bench.BenchmarkTabular.peakmem_IndexTrainTestLeakage('avocado')", "last_rev": 1221, "last_value": 354689024.0, "last_err": 0.0, "prev_value": null, "change_rev": null}, {"name": "tabular_bench.BenchmarkTabular.peakmem_IsSingleValue", "idx": 0, "pretty_name": "tabular_bench.BenchmarkTabular.peakmem_IsSingleValue('lending_club')", "last_rev": 1221, "last_value": 360505344.0, "last_err": 0.0, "prev_value": null, "change_rev": null}, {"name": "tabular_bench.BenchmarkTabular.peakmem_IsSingleValue", "idx": 1, "pretty_name": "tabular_bench.BenchmarkTabular.peakmem_IsSingleValue('avocado')", "last_rev": 1221, "last_value": 354693120.0, "last_err": 0.0, "prev_value": null, "change_rev": null}, {"name": "tabular_bench.BenchmarkTabular.peakmem_MixedDataTypes", "idx": 0, "pretty_name": "tabular_bench.BenchmarkTabular.peakmem_MixedDataTypes('lending_club')", "last_rev": 1221, "last_value": 360218624.0, "last_err": 0.0, "prev_value": null, "change_rev": null}, {"name": "tabular_bench.BenchmarkTabular.peakmem_MixedDataTypes", "idx": 1, "pretty_name": "tabular_bench.BenchmarkTabular.peakmem_MixedDataTypes('avocado')", "last_rev": 1221, "last_value": 354426880.0, "last_err": 0.0, "prev_value": null, "change_rev": null}, {"name": "tabular_bench.BenchmarkTabular.peakmem_MixedNulls", "idx": 0, "pretty_name": "tabular_bench.BenchmarkTabular.peakmem_MixedNulls('lending_club')", "last_rev": 1221, "last_value": 361635840.0, "last_err": 0.0, "prev_value": null, "change_rev": null}, {"name": "tabular_bench.BenchmarkTabular.peakmem_MixedNulls", "idx": 1, "pretty_name": "tabular_bench.BenchmarkTabular.peakmem_MixedNulls('avocado')", "last_rev": 1221, "last_value": 354689024.0, "last_err": 0.0, "prev_value": null, "change_rev": null}, {"name": "tabular_bench.BenchmarkTabular.peakmem_ModelInferenceTime", "idx": 0, "pretty_name": "tabular_bench.BenchmarkTabular.peakmem_ModelInferenceTime('lending_club')", "last_rev": 1221, "last_value": 354156544.0, "last_err": 0.0, "prev_value": null, "change_rev": null}, {"name": "tabular_bench.BenchmarkTabular.peakmem_ModelInferenceTime", "idx": 1, "pretty_name": "tabular_bench.BenchmarkTabular.peakmem_ModelInferenceTime('avocado')", "last_rev": 1221, "last_value": 352292864.0, "last_err": 0.0, "prev_value": null, "change_rev": null}, {"name": "tabular_bench.BenchmarkTabular.peakmem_ModelInfo", "idx": 0, "pretty_name": "tabular_bench.BenchmarkTabular.peakmem_ModelInfo('lending_club')", "last_rev": 1221, "last_value": 353538048.0, "last_err": 0.0, "prev_value": null, "change_rev": null}, {"name": "tabular_bench.BenchmarkTabular.peakmem_ModelInfo", "idx": 1, "pretty_name": "tabular_bench.BenchmarkTabular.peakmem_ModelInfo('avocado')", "last_rev": 1221, "last_value": 350781440.0, "last_err": 0.0, "prev_value": null, "change_rev": null}, {"name": "tabular_bench.BenchmarkTabular.peakmem_MultiModelPerformanceReport", "idx": 0, "pretty_name": "tabular_bench.BenchmarkTabular.peakmem_MultiModelPerformanceReport('lending_club')", "last_rev": null, "last_value": null, "last_err": null, "prev_value": null, "change_rev": null}, {"name": "tabular_bench.BenchmarkTabular.peakmem_MultiModelPerformanceReport", "idx": 1, "pretty_name": "tabular_bench.BenchmarkTabular.peakmem_MultiModelPerformanceReport('avocado')", "last_rev": null, "last_value": null, "last_err": null, "prev_value": null, "change_rev": null}, {"name": "tabular_bench.BenchmarkTabular.peakmem_MultivariateDrift", "idx": 0, "pretty_name": "tabular_bench.BenchmarkTabular.peakmem_MultivariateDrift('lending_club')", "last_rev": 1221, "last_value": 382906368.0, "last_err": 0.0, "prev_value": null, "change_rev": null}, {"name": "tabular_bench.BenchmarkTabular.peakmem_MultivariateDrift", "idx": 1, "pretty_name": "tabular_bench.BenchmarkTabular.peakmem_MultivariateDrift('avocado')", "last_rev": 1221, "last_value": 365637632.0, "last_err": 0.0, "prev_value": null, "change_rev": null}, {"name": "tabular_bench.BenchmarkTabular.peakmem_NewCategoryTrainTest", "idx": 0, "pretty_name": "tabular_bench.BenchmarkTabular.peakmem_NewCategoryTrainTest('lending_club')", "last_rev": 1221, "last_value": 362299392.0, "last_err": 0.0, "prev_value": null, "change_rev": null}, {"name": "tabular_bench.BenchmarkTabular.peakmem_NewCategoryTrainTest", "idx": 1, "pretty_name": "tabular_bench.BenchmarkTabular.peakmem_NewCategoryTrainTest('avocado')", "last_rev": 1221, "last_value": 355692544.0, "last_err": 0.0, "prev_value": null, "change_rev": null}, {"name": "tabular_bench.BenchmarkTabular.peakmem_NewLabelTrainTest", "idx": 0, "pretty_name": "tabular_bench.BenchmarkTabular.peakmem_NewLabelTrainTest('lending_club')", "last_rev": 1221, "last_value": 361422848.0, "last_err": 0.0, "prev_value": null, "change_rev": null}, {"name": "tabular_bench.BenchmarkTabular.peakmem_NewLabelTrainTest", "idx": 1, "pretty_name": "tabular_bench.BenchmarkTabular.peakmem_NewLabelTrainTest('avocado')", "last_rev": 1221, "last_value": 355078144.0, "last_err": 0.0, "prev_value": null, "change_rev": null}, {"name": "tabular_bench.BenchmarkTabular.peakmem_OutlierSampleDetection", "idx": 0, "pretty_name": "tabular_bench.BenchmarkTabular.peakmem_OutlierSampleDetection('lending_club')", "last_rev": 1221, "last_value": 367792128.0, "last_err": 0.0, "prev_value": null, "change_rev": null}, {"name": "tabular_bench.BenchmarkTabular.peakmem_OutlierSampleDetection", "idx": 1, "pretty_name": "tabular_bench.BenchmarkTabular.peakmem_OutlierSampleDetection('avocado')", "last_rev": 1221, "last_value": 363950080.0, "last_err": 0.0, "prev_value": null, "change_rev": null}, {"name": "tabular_bench.BenchmarkTabular.peakmem_PercentOfNulls", "idx": 0, "pretty_name": "tabular_bench.BenchmarkTabular.peakmem_PercentOfNulls('lending_club')", "last_rev": 1221, "last_value": 373690368.0, "last_err": 0.0, "prev_value": null, "change_rev": null}, {"name": "tabular_bench.BenchmarkTabular.peakmem_PercentOfNulls", "idx": 1, "pretty_name": "tabular_bench.BenchmarkTabular.peakmem_PercentOfNulls('avocado')", "last_rev": 1221, "last_value": 354844672.0, "last_err": 0.0, "prev_value": null, "change_rev": null}, {"name": "tabular_bench.BenchmarkTabular.peakmem_RegressionErrorDistribution", "idx": 0, "pretty_name": "tabular_bench.BenchmarkTabular.peakmem_RegressionErrorDistribution('lending_club')", "last_rev": 1221, "last_value": 360116224.0, "last_err": 0.0, "prev_value": null, "change_rev": null}, {"name": "tabular_bench.BenchmarkTabular.peakmem_RegressionErrorDistribution", "idx": 1, "pretty_name": "tabular_bench.BenchmarkTabular.peakmem_RegressionErrorDistribution('avocado')", "last_rev": 1221, "last_value": 391467008.0, "last_err": 0.0, "prev_value": null, "change_rev": null}, {"name": "tabular_bench.BenchmarkTabular.peakmem_RegressionSystematicError", "idx": 0, "pretty_name": "tabular_bench.BenchmarkTabular.peakmem_RegressionSystematicError('lending_club')", "last_rev": 1221, "last_value": 360169472.0, "last_err": 0.0, "prev_value": null, "change_rev": null}, {"name": "tabular_bench.BenchmarkTabular.peakmem_RegressionSystematicError", "idx": 1, "pretty_name": "tabular_bench.BenchmarkTabular.peakmem_RegressionSystematicError('avocado')", "last_rev": 1221, "last_value": 381382656.0, "last_err": 0.0, "prev_value": null, "change_rev": null}, {"name": "tabular_bench.BenchmarkTabular.peakmem_RocReport", "idx": 0, "pretty_name": "tabular_bench.BenchmarkTabular.peakmem_RocReport('lending_club')", "last_rev": 1221, "last_value": 368037888.0, "last_err": 0.0, "prev_value": null, "change_rev": null}, {"name": "tabular_bench.BenchmarkTabular.peakmem_RocReport", "idx": 1, "pretty_name": "tabular_bench.BenchmarkTabular.peakmem_RocReport('avocado')", "last_rev": 1221, "last_value": 354344960.0, "last_err": 0.0, "prev_value": null, "change_rev": null}, {"name": "tabular_bench.BenchmarkTabular.peakmem_SegmentPerformance", "idx": 0, "pretty_name": "tabular_bench.BenchmarkTabular.peakmem_SegmentPerformance('lending_club')", "last_rev": 1221, "last_value": 376975360.0, "last_err": 0.0, "prev_value": null, "change_rev": null}, {"name": "tabular_bench.BenchmarkTabular.peakmem_SegmentPerformance", "idx": 1, "pretty_name": "tabular_bench.BenchmarkTabular.peakmem_SegmentPerformance('avocado')", "last_rev": 1221, "last_value": 369876992.0, "last_err": 0.0, "prev_value": null, "change_rev": null}, {"name": "tabular_bench.BenchmarkTabular.peakmem_SimpleModelComparison", "idx": 0, "pretty_name": "tabular_bench.BenchmarkTabular.peakmem_SimpleModelComparison('lending_club')", "last_rev": 1221, "last_value": 380059648.0, "last_err": 0.0, "prev_value": null, "change_rev": null}, {"name": "tabular_bench.BenchmarkTabular.peakmem_SimpleModelComparison", "idx": 1, "pretty_name": "tabular_bench.BenchmarkTabular.peakmem_SimpleModelComparison('avocado')", "last_rev": 1221, "last_value": 373604352.0, "last_err": 0.0, "prev_value": null, "change_rev": null}, {"name": "tabular_bench.BenchmarkTabular.peakmem_SingleDatasetPerformance", "idx": 0, "pretty_name": "tabular_bench.BenchmarkTabular.peakmem_SingleDatasetPerformance('lending_club')", "last_rev": 1221, "last_value": 371847168.0, "last_err": 0.0, "prev_value": null, "change_rev": null}, {"name": "tabular_bench.BenchmarkTabular.peakmem_SingleDatasetPerformance", "idx": 1, "pretty_name": "tabular_bench.BenchmarkTabular.peakmem_SingleDatasetPerformance('avocado')", "last_rev": 1221, "last_value": 384016384.0, "last_err": 0.0, "prev_value": null, "change_rev": null}, {"name": "tabular_bench.BenchmarkTabular.peakmem_SpecialCharacters", "idx": 0, "pretty_name": "tabular_bench.BenchmarkTabular.peakmem_SpecialCharacters('lending_club')", "last_rev": 1221, "last_value": 361660416.0, "last_err": 0.0, "prev_value": null, "change_rev": null}, {"name": "tabular_bench.BenchmarkTabular.peakmem_SpecialCharacters", "idx": 1, "pretty_name": "tabular_bench.BenchmarkTabular.peakmem_SpecialCharacters('avocado')", "last_rev": 1221, "last_value": 355635200.0, "last_err": 0.0, "prev_value": null, "change_rev": null}, {"name": "tabular_bench.BenchmarkTabular.peakmem_StringLengthOutOfBounds", "idx": 0, "pretty_name": "tabular_bench.BenchmarkTabular.peakmem_StringLengthOutOfBounds('lending_club')", "last_rev": 1221, "last_value": 360218624.0, "last_err": 0.0, "prev_value": null, "change_rev": null}, {"name": "tabular_bench.BenchmarkTabular.peakmem_StringLengthOutOfBounds", "idx": 1, "pretty_name": "tabular_bench.BenchmarkTabular.peakmem_StringLengthOutOfBounds('avocado')", "last_rev": 1221, "last_value": 354492416.0, "last_err": 0.0, "prev_value": null, "change_rev": null}, {"name": "tabular_bench.BenchmarkTabular.peakmem_StringMismatch", "idx": 0, "pretty_name": "tabular_bench.BenchmarkTabular.peakmem_StringMismatch('lending_club')", "last_rev": 1221, "last_value": 360353792.0, "last_err": 0.0, "prev_value": null, "change_rev": null}, {"name": "tabular_bench.BenchmarkTabular.peakmem_StringMismatch", "idx": 1, "pretty_name": "tabular_bench.BenchmarkTabular.peakmem_StringMismatch('avocado')", "last_rev": 1221, "last_value": 354598912.0, "last_err": 0.0, "prev_value": null, "change_rev": null}, {"name": "tabular_bench.BenchmarkTabular.peakmem_StringMismatchComparison", "idx": 0, "pretty_name": "tabular_bench.BenchmarkTabular.peakmem_StringMismatchComparison('lending_club')", "last_rev": 1221, "last_value": 361865216.0, "last_err": 0.0, "prev_value": null, "change_rev": null}, {"name": "tabular_bench.BenchmarkTabular.peakmem_StringMismatchComparison", "idx": 1, "pretty_name": "tabular_bench.BenchmarkTabular.peakmem_StringMismatchComparison('avocado')", "last_rev": 1221, "last_value": 355262464.0, "last_err": 0.0, "prev_value": null, "change_rev": null}, {"name": "tabular_bench.BenchmarkTabular.peakmem_TrainTestFeatureDrift", "idx": 0, "pretty_name": "tabular_bench.BenchmarkTabular.peakmem_TrainTestFeatureDrift('lending_club')", "last_rev": 1221, "last_value": 370556928.0, "last_err": 0.0, "prev_value": null, "change_rev": null}, {"name": "tabular_bench.BenchmarkTabular.peakmem_TrainTestFeatureDrift", "idx": 1, "pretty_name": "tabular_bench.BenchmarkTabular.peakmem_TrainTestFeatureDrift('avocado')", "last_rev": 1221, "last_value": 365027328.0, "last_err": 0.0, "prev_value": null, "change_rev": null}, {"name": "tabular_bench.BenchmarkTabular.peakmem_TrainTestLabelDrift", "idx": 0, "pretty_name": "tabular_bench.BenchmarkTabular.peakmem_TrainTestLabelDrift('lending_club')", "last_rev": 1221, "last_value": 363294720.0, "last_err": 0.0, "prev_value": null, "change_rev": null}, {"name": "tabular_bench.BenchmarkTabular.peakmem_TrainTestLabelDrift", "idx": 1, "pretty_name": "tabular_bench.BenchmarkTabular.peakmem_TrainTestLabelDrift('avocado')", "last_rev": 1221, "last_value": 361799680.0, "last_err": 0.0, "prev_value": null, "change_rev": null}, {"name": "tabular_bench.BenchmarkTabular.peakmem_TrainTestPerformance", "idx": 0, "pretty_name": "tabular_bench.BenchmarkTabular.peakmem_TrainTestPerformance('lending_club')", "last_rev": 1221, "last_value": 382619648.0, "last_err": 0.0, "prev_value": null, "change_rev": null}, {"name": "tabular_bench.BenchmarkTabular.peakmem_TrainTestPerformance", "idx": 1, "pretty_name": "tabular_bench.BenchmarkTabular.peakmem_TrainTestPerformance('avocado')", "last_rev": 1221, "last_value": 394383360.0, "last_err": 0.0, "prev_value": null, "change_rev": null}, {"name": "tabular_bench.BenchmarkTabular.peakmem_TrainTestPredictionDrift", "idx": 0, "pretty_name": "tabular_bench.BenchmarkTabular.peakmem_TrainTestPredictionDrift('lending_club')", "last_rev": 1221, "last_value": 375947264.0, "last_err": 0.0, "prev_value": null, "change_rev": null}, {"name": "tabular_bench.BenchmarkTabular.peakmem_TrainTestPredictionDrift", "idx": 1, "pretty_name": "tabular_bench.BenchmarkTabular.peakmem_TrainTestPredictionDrift('avocado')", "last_rev": 1221, "last_value": 387215360.0, "last_err": 0.0, "prev_value": null, "change_rev": null}, {"name": "tabular_bench.BenchmarkTabular.peakmem_TrainTestSamplesMix", "idx": 0, "pretty_name": "tabular_bench.BenchmarkTabular.peakmem_TrainTestSamplesMix('lending_club')", "last_rev": 1221, "last_value": 431423488.0, "last_err": 0.0, "prev_value": null, "change_rev": null}, {"name": "tabular_bench.BenchmarkTabular.peakmem_TrainTestSamplesMix", "idx": 1, "pretty_name": "tabular_bench.BenchmarkTabular.peakmem_TrainTestSamplesMix('avocado')", "last_rev": 1221, "last_value": 400474112.0, "last_err": 0.0, "prev_value": null, "change_rev": null}, {"name": "tabular_bench.BenchmarkTabular.peakmem_UnusedFeatures", "idx": 0, "pretty_name": "tabular_bench.BenchmarkTabular.peakmem_UnusedFeatures('lending_club')", "last_rev": 1221, "last_value": 394645504.0, "last_err": 0.0, "prev_value": null, "change_rev": null}, {"name": "tabular_bench.BenchmarkTabular.peakmem_UnusedFeatures", "idx": 1, "pretty_name": "tabular_bench.BenchmarkTabular.peakmem_UnusedFeatures('avocado')", "last_rev": 1221, "last_value": 376975360.0, "last_err": 0.0, "prev_value": null, "change_rev": null}, {"name": "tabular_bench.BenchmarkTabular.peakmem_WeakSegmentsPerformance", "idx": 0, "pretty_name": "tabular_bench.BenchmarkTabular.peakmem_WeakSegmentsPerformance('lending_club')", "last_rev": 1221, "last_value": 388362240.0, "last_err": 0.0, "prev_value": null, "change_rev": null}, {"name": "tabular_bench.BenchmarkTabular.peakmem_WeakSegmentsPerformance", "idx": 1, "pretty_name": "tabular_bench.BenchmarkTabular.peakmem_WeakSegmentsPerformance('avocado')", "last_rev": 1221, "last_value": 395735040.0, "last_err": 0.0, "prev_value": null, "change_rev": null}, {"name": "tabular_bench.BenchmarkTabular.peakmem_WholeDatasetDrift", "idx": 0, "pretty_name": "tabular_bench.BenchmarkTabular.peakmem_WholeDatasetDrift('lending_club')", "last_rev": 1221, "last_value": 383045632.0, "last_err": 0.0, "prev_value": null, "change_rev": null}, {"name": "tabular_bench.BenchmarkTabular.peakmem_WholeDatasetDrift", "idx": 1, "pretty_name": "tabular_bench.BenchmarkTabular.peakmem_WholeDatasetDrift('avocado')", "last_rev": 1221, "last_value": 365735936.0, "last_err": 0.0, "prev_value": null, "change_rev": null}, {"name": "tabular_bench.BenchmarkTabular.time_BoostingOverfit", "idx": 0, "pretty_name": "tabular_bench.BenchmarkTabular.time_BoostingOverfit('lending_club')", "last_rev": 1221, "last_value": 0.039244707000008816, "last_err": 0.0, "prev_value": null, "change_rev": null}, {"name": "tabular_bench.BenchmarkTabular.time_BoostingOverfit", "idx": 1, "pretty_name": "tabular_bench.BenchmarkTabular.time_BoostingOverfit('avocado')", "last_rev": 1221, "last_value": 0.03497541999996656, "last_err": 0.0, "prev_value": null, "change_rev": null}, {"name": "tabular_bench.BenchmarkTabular.time_CalibrationScore", "idx": 0, "pretty_name": "tabular_bench.BenchmarkTabular.time_CalibrationScore('lending_club')", "last_rev": 1221, "last_value": 0.11186706349997166, "last_err": 0.0, "prev_value": null, "change_rev": null}, {"name": "tabular_bench.BenchmarkTabular.time_CalibrationScore", "idx": 1, "pretty_name": "tabular_bench.BenchmarkTabular.time_CalibrationScore('avocado')", "last_rev": 1221, "last_value": 0.012483298000034893, "last_err": 0.0, "prev_value": null, "change_rev": null}, {"name": "tabular_bench.BenchmarkTabular.time_CategoryMismatchTrainTest", "idx": 0, "pretty_name": "tabular_bench.BenchmarkTabular.time_CategoryMismatchTrainTest('lending_club')", "last_rev": 1221, "last_value": 0.04666611099997908, "last_err": 0.0, "prev_value": null, "change_rev": null}, {"name": "tabular_bench.BenchmarkTabular.time_CategoryMismatchTrainTest", "idx": 1, "pretty_name": "tabular_bench.BenchmarkTabular.time_CategoryMismatchTrainTest('avocado')", "last_rev": 1221, "last_value": 0.027087115000000495, "last_err": 0.0, "prev_value": null, "change_rev": null}, {"name": "tabular_bench.BenchmarkTabular.time_ClassImbalance", "idx": 0, "pretty_name": "tabular_bench.BenchmarkTabular.time_ClassImbalance('lending_club')", "last_rev": 1221, "last_value": 0.03911495649998642, "last_err": 0.0, "prev_value": null, "change_rev": null}, {"name": "tabular_bench.BenchmarkTabular.time_ClassImbalance", "idx": 1, "pretty_name": "tabular_bench.BenchmarkTabular.time_ClassImbalance('avocado')", "last_rev": 1221, "last_value": 4.17614650537606e-06, "last_err": 0.0, "prev_value": null, "change_rev": null}, {"name": "tabular_bench.BenchmarkTabular.time_ColumnsInfo", "idx": 0, "pretty_name": "tabular_bench.BenchmarkTabular.time_ColumnsInfo('lending_club')", "last_rev": 1221, "last_value": 0.0008280141538425422, "last_err": 0.0, "prev_value": null, "change_rev": null}, {"name": "tabular_bench.BenchmarkTabular.time_ColumnsInfo", "idx": 1, "pretty_name": "tabular_bench.BenchmarkTabular.time_ColumnsInfo('avocado')", "last_rev": 1221, "last_value": 0.0007465271071416574, "last_err": 0.0, "prev_value": null, "change_rev": null}, {"name": "tabular_bench.BenchmarkTabular.time_ConflictingLabels", "idx": 0, "pretty_name": "tabular_bench.BenchmarkTabular.time_ConflictingLabels('lending_club')", "last_rev": 1221, "last_value": 1.7719965260000095, "last_err": 0.0, "prev_value": null, "change_rev": null}, {"name": "tabular_bench.BenchmarkTabular.time_ConflictingLabels", "idx": 1, "pretty_name": "tabular_bench.BenchmarkTabular.time_ConflictingLabels('avocado')", "last_rev": 1221, "last_value": 4.409539850561069e-06, "last_err": 0.0, "prev_value": null, "change_rev": null}, {"name": "tabular_bench.BenchmarkTabular.time_ConfusionMatrixReport", "idx": 0, "pretty_name": "tabular_bench.BenchmarkTabular.time_ConfusionMatrixReport('lending_club')", "last_rev": 1221, "last_value": 0.10789942799999608, "last_err": 0.0, "prev_value": null, "change_rev": null}, {"name": "tabular_bench.BenchmarkTabular.time_ConfusionMatrixReport", "idx": 1, "pretty_name": "tabular_bench.BenchmarkTabular.time_ConfusionMatrixReport('avocado')", "last_rev": 1221, "last_value": 0.012583497999997917, "last_err": 0.0, "prev_value": null, "change_rev": null}, {"name": "tabular_bench.BenchmarkTabular.time_DataDuplicates", "idx": 0, "pretty_name": "tabular_bench.BenchmarkTabular.time_DataDuplicates('lending_club')", "last_rev": 1221, "last_value": 0.05328830950003294, "last_err": 0.0, "prev_value": null, "change_rev": null}, {"name": "tabular_bench.BenchmarkTabular.time_DataDuplicates", "idx": 1, "pretty_name": "tabular_bench.BenchmarkTabular.time_DataDuplicates('avocado')", "last_rev": 1221, "last_value": 0.043820186000033345, "last_err": 0.0, "prev_value": null, "change_rev": null}, {"name": "tabular_bench.BenchmarkTabular.time_DatasetsSizeComparison", "idx": 0, "pretty_name": "tabular_bench.BenchmarkTabular.time_DatasetsSizeComparison('lending_club')", "last_rev": 1221, "last_value": 0.0002033342346935894, "last_err": 0.0, "prev_value": null, "change_rev": null}, {"name": "tabular_bench.BenchmarkTabular.time_DatasetsSizeComparison", "idx": 1, "pretty_name": "tabular_bench.BenchmarkTabular.time_DatasetsSizeComparison('avocado')", "last_rev": 1221, "last_value": 0.00020270755999945322, "last_err": 0.0, "prev_value": null, "change_rev": null}, {"name": "tabular_bench.BenchmarkTabular.time_DateTrainTestLeakageDuplicates", "idx": 0, "pretty_name": "tabular_bench.BenchmarkTabular.time_DateTrainTestLeakageDuplicates('lending_club')", "last_rev": 1221, "last_value": 0.04561110449998296, "last_err": 0.0, "prev_value": null, "change_rev": null}, {"name": "tabular_bench.BenchmarkTabular.time_DateTrainTestLeakageDuplicates", "idx": 1, "pretty_name": "tabular_bench.BenchmarkTabular.time_DateTrainTestLeakageDuplicates('avocado')", "last_rev": 1221, "last_value": 0.06365348900001777, "last_err": 0.0, "prev_value": null, "change_rev": null}, {"name": "tabular_bench.BenchmarkTabular.time_DateTrainTestLeakageOverlap", "idx": 0, "pretty_name": "tabular_bench.BenchmarkTabular.time_DateTrainTestLeakageOverlap('lending_club')", "last_rev": 1221, "last_value": 0.046826809500004174, "last_err": 0.0, "prev_value": null, "change_rev": null}, {"name": "tabular_bench.BenchmarkTabular.time_DateTrainTestLeakageOverlap", "idx": 1, "pretty_name": "tabular_bench.BenchmarkTabular.time_DateTrainTestLeakageOverlap('avocado')", "last_rev": 1221, "last_value": 0.03914480099999196, "last_err": 0.0, "prev_value": null, "change_rev": null}, {"name": "tabular_bench.BenchmarkTabular.time_FeatureFeatureCorrelation", "idx": 0, "pretty_name": "tabular_bench.BenchmarkTabular.time_FeatureFeatureCorrelation('lending_club')", "last_rev": 1221, "last_value": 0.7419118490000187, "last_err": 0.0, "prev_value": null, "change_rev": null}, {"name": "tabular_bench.BenchmarkTabular.time_FeatureFeatureCorrelation", "idx": 1, "pretty_name": "tabular_bench.BenchmarkTabular.time_FeatureFeatureCorrelation('avocado')", "last_rev": 1221, "last_value": 0.11574968800002239, "last_err": 0.0, "prev_value": null, "change_rev": null}, {"name": "tabular_bench.BenchmarkTabular.time_FeatureLabelCorrelation", "idx": 0, "pretty_name": "tabular_bench.BenchmarkTabular.time_FeatureLabelCorrelation('lending_club')", "last_rev": 1221, "last_value": 0.5133087875000228, "last_err": 0.0, "prev_value": null, "change_rev": null}, {"name": "tabular_bench.BenchmarkTabular.time_FeatureLabelCorrelation", "idx": 1, "pretty_name": "tabular_bench.BenchmarkTabular.time_FeatureLabelCorrelation('avocado')", "last_rev": 1221, "last_value": 0.33263592050005286, "last_err": 0.0, "prev_value": null, "change_rev": null}, {"name": "tabular_bench.BenchmarkTabular.time_FeatureLabelCorrelationChange", "idx": 0, "pretty_name": "tabular_bench.BenchmarkTabular.time_FeatureLabelCorrelationChange('lending_club')", "last_rev": 1221, "last_value": 1.0062143389999676, "last_err": 0.0, "prev_value": null, "change_rev": null}, {"name": "tabular_bench.BenchmarkTabular.time_FeatureLabelCorrelationChange", "idx": 1, "pretty_name": "tabular_bench.BenchmarkTabular.time_FeatureLabelCorrelationChange('avocado')", "last_rev": 1221, "last_value": 0.6235268124999607, "last_err": 0.0, "prev_value": null, "change_rev": null}, {"name": "tabular_bench.BenchmarkTabular.time_IdentifierLabelCorrelation", "idx": 0, "pretty_name": "tabular_bench.BenchmarkTabular.time_IdentifierLabelCorrelation('lending_club')", "last_rev": 1221, "last_value": 0.11407180950001816, "last_err": 0.0, "prev_value": null, "change_rev": null}, {"name": "tabular_bench.BenchmarkTabular.time_IdentifierLabelCorrelation", "idx": 1, "pretty_name": "tabular_bench.BenchmarkTabular.time_IdentifierLabelCorrelation('avocado')", "last_rev": 1221, "last_value": 0.07522266700001978, "last_err": 0.0, "prev_value": null, "change_rev": null}, {"name": "tabular_bench.BenchmarkTabular.time_IndexTrainTestLeakage", "idx": 0, "pretty_name": "tabular_bench.BenchmarkTabular.time_IndexTrainTestLeakage('lending_club')", "last_rev": 1221, "last_value": 0.026758357000005617, "last_err": 0.0, "prev_value": null, "change_rev": null}, {"name": "tabular_bench.BenchmarkTabular.time_IndexTrainTestLeakage", "idx": 1, "pretty_name": "tabular_bench.BenchmarkTabular.time_IndexTrainTestLeakage('avocado')", "last_rev": 1221, "last_value": 0.018987640000005968, "last_err": 0.0, "prev_value": null, "change_rev": null}, {"name": "tabular_bench.BenchmarkTabular.time_IsSingleValue", "idx": 0, "pretty_name": "tabular_bench.BenchmarkTabular.time_IsSingleValue('lending_club')", "last_rev": 1221, "last_value": 0.02774550399999498, "last_err": 0.0, "prev_value": null, "change_rev": null}, {"name": "tabular_bench.BenchmarkTabular.time_IsSingleValue", "idx": 1, "pretty_name": "tabular_bench.BenchmarkTabular.time_IsSingleValue('avocado')", "last_rev": 1221, "last_value": 0.01863858700002652, "last_err": 0.0, "prev_value": null, "change_rev": null}, {"name": "tabular_bench.BenchmarkTabular.time_MixedDataTypes", "idx": 0, "pretty_name": "tabular_bench.BenchmarkTabular.time_MixedDataTypes('lending_club')", "last_rev": 1221, "last_value": 0.16517119499999922, "last_err": 0.0, "prev_value": null, "change_rev": null}, {"name": "tabular_bench.BenchmarkTabular.time_MixedDataTypes", "idx": 1, "pretty_name": "tabular_bench.BenchmarkTabular.time_MixedDataTypes('avocado')", "last_rev": 1221, "last_value": 0.04727994749998743, "last_err": 0.0, "prev_value": null, "change_rev": null}, {"name": "tabular_bench.BenchmarkTabular.time_MixedNulls", "idx": 0, "pretty_name": "tabular_bench.BenchmarkTabular.time_MixedNulls('lending_club')", "last_rev": 1221, "last_value": 0.07794398600000818, "last_err": 0.0, "prev_value": null, "change_rev": null}, {"name": "tabular_bench.BenchmarkTabular.time_MixedNulls", "idx": 1, "pretty_name": "tabular_bench.BenchmarkTabular.time_MixedNulls('avocado')", "last_rev": 1221, "last_value": 0.07531016600003682, "last_err": 0.0, "prev_value": null, "change_rev": null}, {"name": "tabular_bench.BenchmarkTabular.time_ModelInferenceTime", "idx": 0, "pretty_name": "tabular_bench.BenchmarkTabular.time_ModelInferenceTime('lending_club')", "last_rev": 1221, "last_value": 0.017329180500013308, "last_err": 0.0, "prev_value": null, "change_rev": null}, {"name": "tabular_bench.BenchmarkTabular.time_ModelInferenceTime", "idx": 1, "pretty_name": "tabular_bench.BenchmarkTabular.time_ModelInferenceTime('avocado')", "last_rev": 1221, "last_value": 0.01550101899999845, "last_err": 0.0, "prev_value": null, "change_rev": null}, {"name": "tabular_bench.BenchmarkTabular.time_ModelInfo", "idx": 0, "pretty_name": "tabular_bench.BenchmarkTabular.time_ModelInfo('lending_club')", "last_rev": 1221, "last_value": 0.0009639799545430544, "last_err": 0.0, "prev_value": null, "change_rev": null}, {"name": "tabular_bench.BenchmarkTabular.time_ModelInfo", "idx": 1, "pretty_name": "tabular_bench.BenchmarkTabular.time_ModelInfo('avocado')", "last_rev": 1221, "last_value": 0.0009643483636394153, "last_err": 0.0, "prev_value": null, "change_rev": null}, {"name": "tabular_bench.BenchmarkTabular.time_MultiModelPerformanceReport", "idx": 0, "pretty_name": "tabular_bench.BenchmarkTabular.time_MultiModelPerformanceReport('lending_club')", "last_rev": null, "last_value": null, "last_err": null, "prev_value": null, "change_rev": null}, {"name": "tabular_bench.BenchmarkTabular.time_MultiModelPerformanceReport", "idx": 1, "pretty_name": "tabular_bench.BenchmarkTabular.time_MultiModelPerformanceReport('avocado')", "last_rev": null, "last_value": null, "last_err": null, "prev_value": null, "change_rev": null}, {"name": "tabular_bench.BenchmarkTabular.time_MultivariateDrift", "idx": 0, "pretty_name": "tabular_bench.BenchmarkTabular.time_MultivariateDrift('lending_club')", "last_rev": 1221, "last_value": 0.7695340180000301, "last_err": 0.0, "prev_value": null, "change_rev": null}, {"name": "tabular_bench.BenchmarkTabular.time_MultivariateDrift", "idx": 1, "pretty_name": "tabular_bench.BenchmarkTabular.time_MultivariateDrift('avocado')", "last_rev": 1221, "last_value": 0.34408037349999177, "last_err": 0.0, "prev_value": null, "change_rev": null}, {"name": "tabular_bench.BenchmarkTabular.time_NewCategoryTrainTest", "idx": 0, "pretty_name": "tabular_bench.BenchmarkTabular.time_NewCategoryTrainTest('lending_club')", "last_rev": 1221, "last_value": 0.04666961699999206, "last_err": 0.0, "prev_value": null, "change_rev": null}, {"name": "tabular_bench.BenchmarkTabular.time_NewCategoryTrainTest", "idx": 1, "pretty_name": "tabular_bench.BenchmarkTabular.time_NewCategoryTrainTest('avocado')", "last_rev": 1221, "last_value": 0.027111557000012, "last_err": 0.0, "prev_value": null, "change_rev": null}, {"name": "tabular_bench.BenchmarkTabular.time_NewLabelTrainTest", "idx": 0, "pretty_name": "tabular_bench.BenchmarkTabular.time_NewLabelTrainTest('lending_club')", "last_rev": 1221, "last_value": 0.023611885500002927, "last_err": 0.0, "prev_value": null, "change_rev": null}, {"name": "tabular_bench.BenchmarkTabular.time_NewLabelTrainTest", "idx": 1, "pretty_name": "tabular_bench.BenchmarkTabular.time_NewLabelTrainTest('avocado')", "last_rev": 1221, "last_value": 0.01888294349998887, "last_err": 0.0, "prev_value": null, "change_rev": null}, {"name": "tabular_bench.BenchmarkTabular.time_OutlierSampleDetection", "idx": 0, "pretty_name": "tabular_bench.BenchmarkTabular.time_OutlierSampleDetection('lending_club')", "last_rev": 1221, "last_value": 6.042241933000014, "last_err": 0.0, "prev_value": null, "change_rev": null}, {"name": "tabular_bench.BenchmarkTabular.time_OutlierSampleDetection", "idx": 1, "pretty_name": "tabular_bench.BenchmarkTabular.time_OutlierSampleDetection('avocado')", "last_rev": 1221, "last_value": 2.93808498300001, "last_err": 0.0, "prev_value": null, "change_rev": null}, {"name": "tabular_bench.BenchmarkTabular.time_PercentOfNulls", "idx": 0, "pretty_name": "tabular_bench.BenchmarkTabular.time_PercentOfNulls('lending_club')", "last_rev": 1221, "last_value": 0.07129602800000612, "last_err": 0.0, "prev_value": null, "change_rev": null}, {"name": "tabular_bench.BenchmarkTabular.time_PercentOfNulls", "idx": 1, "pretty_name": "tabular_bench.BenchmarkTabular.time_PercentOfNulls('avocado')", "last_rev": 1221, "last_value": 0.019635950999941088, "last_err": 0.0, "prev_value": null, "change_rev": null}, {"name": "tabular_bench.BenchmarkTabular.time_RegressionErrorDistribution", "idx": 0, "pretty_name": "tabular_bench.BenchmarkTabular.time_RegressionErrorDistribution('lending_club')", "last_rev": 1221, "last_value": 0.015172415999984423, "last_err": 0.0, "prev_value": null, "change_rev": null}, {"name": "tabular_bench.BenchmarkTabular.time_RegressionErrorDistribution", "idx": 1, "pretty_name": "tabular_bench.BenchmarkTabular.time_RegressionErrorDistribution('avocado')", "last_rev": 1221, "last_value": 0.1181800559999715, "last_err": 0.0, "prev_value": null, "change_rev": null}, {"name": "tabular_bench.BenchmarkTabular.time_RegressionSystematicError", "idx": 0, "pretty_name": "tabular_bench.BenchmarkTabular.time_RegressionSystematicError('lending_club')", "last_rev": 1221, "last_value": 0.01490831800003889, "last_err": 0.0, "prev_value": null, "change_rev": null}, {"name": "tabular_bench.BenchmarkTabular.time_RegressionSystematicError", "idx": 1, "pretty_name": "tabular_bench.BenchmarkTabular.time_RegressionSystematicError('avocado')", "last_rev": 1221, "last_value": 0.06667334099998357, "last_err": 0.0, "prev_value": null, "change_rev": null}, {"name": "tabular_bench.BenchmarkTabular.time_RocReport", "idx": 0, "pretty_name": "tabular_bench.BenchmarkTabular.time_RocReport('lending_club')", "last_rev": 1221, "last_value": 0.11189548249998893, "last_err": 0.0, "prev_value": null, "change_rev": null}, {"name": "tabular_bench.BenchmarkTabular.time_RocReport", "idx": 1, "pretty_name": "tabular_bench.BenchmarkTabular.time_RocReport('avocado')", "last_rev": 1221, "last_value": 0.012533701499990002, "last_err": 0.0, "prev_value": null, "change_rev": null}, {"name": "tabular_bench.BenchmarkTabular.time_SegmentPerformance", "idx": 0, "pretty_name": "tabular_bench.BenchmarkTabular.time_SegmentPerformance('lending_club')", "last_rev": 1221, "last_value": 1.8922999174999973, "last_err": 0.0, "prev_value": null, "change_rev": null}, {"name": "tabular_bench.BenchmarkTabular.time_SegmentPerformance", "idx": 1, "pretty_name": "tabular_bench.BenchmarkTabular.time_SegmentPerformance('avocado')", "last_rev": 1221, "last_value": 0.4072438930000146, "last_err": 0.0, "prev_value": null, "change_rev": null}, {"name": "tabular_bench.BenchmarkTabular.time_SimpleModelComparison", "idx": 0, "pretty_name": "tabular_bench.BenchmarkTabular.time_SimpleModelComparison('lending_club')", "last_rev": 1221, "last_value": 0.17310646699999666, "last_err": 0.0, "prev_value": null, "change_rev": null}, {"name": "tabular_bench.BenchmarkTabular.time_SimpleModelComparison", "idx": 1, "pretty_name": "tabular_bench.BenchmarkTabular.time_SimpleModelComparison('avocado')", "last_rev": 1221, "last_value": 0.133273865499973, "last_err": 0.0, "prev_value": null, "change_rev": null}, {"name": "tabular_bench.BenchmarkTabular.time_SingleDatasetPerformance", "idx": 0, "pretty_name": "tabular_bench.BenchmarkTabular.time_SingleDatasetPerformance('lending_club')", "last_rev": 1221, "last_value": 0.38447531950004077, "last_err": 0.0, "prev_value": null, "change_rev": null}, {"name": "tabular_bench.BenchmarkTabular.time_SingleDatasetPerformance", "idx": 1, "pretty_name": "tabular_bench.BenchmarkTabular.time_SingleDatasetPerformance('avocado')", "last_rev": 1221, "last_value": 0.25337360400001785, "last_err": 0.0, "prev_value": null, "change_rev": null}, {"name": "tabular_bench.BenchmarkTabular.time_SpecialCharacters", "idx": 0, "pretty_name": "tabular_bench.BenchmarkTabular.time_SpecialCharacters('lending_club')", "last_rev": 1221, "last_value": 0.17866389900004265, "last_err": 0.0, "prev_value": null, "change_rev": null}, {"name": "tabular_bench.BenchmarkTabular.time_SpecialCharacters", "idx": 1, "pretty_name": "tabular_bench.BenchmarkTabular.time_SpecialCharacters('avocado')", "last_rev": 1221, "last_value": 0.06281448050003746, "last_err": 0.0, "prev_value": null, "change_rev": null}, {"name": "tabular_bench.BenchmarkTabular.time_StringLengthOutOfBounds", "idx": 0, "pretty_name": "tabular_bench.BenchmarkTabular.time_StringLengthOutOfBounds('lending_club')", "last_rev": 1221, "last_value": 0.026774095999968495, "last_err": 0.0, "prev_value": null, "change_rev": null}, {"name": "tabular_bench.BenchmarkTabular.time_StringLengthOutOfBounds", "idx": 1, "pretty_name": "tabular_bench.BenchmarkTabular.time_StringLengthOutOfBounds('avocado')", "last_rev": 1221, "last_value": 0.01600806700002977, "last_err": 0.0, "prev_value": null, "change_rev": null}, {"name": "tabular_bench.BenchmarkTabular.time_StringMismatch", "idx": 0, "pretty_name": "tabular_bench.BenchmarkTabular.time_StringMismatch('lending_club')", "last_rev": 1221, "last_value": 0.030610513999960176, "last_err": 0.0, "prev_value": null, "change_rev": null}, {"name": "tabular_bench.BenchmarkTabular.time_StringMismatch", "idx": 1, "pretty_name": "tabular_bench.BenchmarkTabular.time_StringMismatch('avocado')", "last_rev": 1221, "last_value": 0.016401325000003908, "last_err": 0.0, "prev_value": null, "change_rev": null}, {"name": "tabular_bench.BenchmarkTabular.time_StringMismatchComparison", "idx": 0, "pretty_name": "tabular_bench.BenchmarkTabular.time_StringMismatchComparison('lending_club')", "last_rev": 1221, "last_value": 0.04642243899996856, "last_err": 0.0, "prev_value": null, "change_rev": null}, {"name": "tabular_bench.BenchmarkTabular.time_StringMismatchComparison", "idx": 1, "pretty_name": "tabular_bench.BenchmarkTabular.time_StringMismatchComparison('avocado')", "last_rev": 1221, "last_value": 0.025291685000041753, "last_err": 0.0, "prev_value": null, "change_rev": null}, {"name": "tabular_bench.BenchmarkTabular.time_TrainTestFeatureDrift", "idx": 0, "pretty_name": "tabular_bench.BenchmarkTabular.time_TrainTestFeatureDrift('lending_club')", "last_rev": 1221, "last_value": 1.7105742400000281, "last_err": 0.0, "prev_value": null, "change_rev": null}, {"name": "tabular_bench.BenchmarkTabular.time_TrainTestFeatureDrift", "idx": 1, "pretty_name": "tabular_bench.BenchmarkTabular.time_TrainTestFeatureDrift('avocado')", "last_rev": 1221, "last_value": 0.9669188755000562, "last_err": 0.0, "prev_value": null, "change_rev": null}, {"name": "tabular_bench.BenchmarkTabular.time_TrainTestLabelDrift", "idx": 0, "pretty_name": "tabular_bench.BenchmarkTabular.time_TrainTestLabelDrift('lending_club')", "last_rev": 1221, "last_value": 0.06884873899997501, "last_err": 0.0, "prev_value": null, "change_rev": null}, {"name": "tabular_bench.BenchmarkTabular.time_TrainTestLabelDrift", "idx": 1, "pretty_name": "tabular_bench.BenchmarkTabular.time_TrainTestLabelDrift('avocado')", "last_rev": 1221, "last_value": 0.12331525150003131, "last_err": 0.0, "prev_value": null, "change_rev": null}, {"name": "tabular_bench.BenchmarkTabular.time_TrainTestPerformance", "idx": 0, "pretty_name": "tabular_bench.BenchmarkTabular.time_TrainTestPerformance('lending_club')", "last_rev": 1221, "last_value": 0.6362349645000336, "last_err": 0.0, "prev_value": null, "change_rev": null}, {"name": "tabular_bench.BenchmarkTabular.time_TrainTestPerformance", "idx": 1, "pretty_name": "tabular_bench.BenchmarkTabular.time_TrainTestPerformance('avocado')", "last_rev": 1221, "last_value": 0.4474973099999602, "last_err": 0.0, "prev_value": null, "change_rev": null}, {"name": "tabular_bench.BenchmarkTabular.time_TrainTestPredictionDrift", "idx": 0, "pretty_name": "tabular_bench.BenchmarkTabular.time_TrainTestPredictionDrift('lending_club')", "last_rev": 1221, "last_value": 0.23331292700001427, "last_err": 0.0, "prev_value": null, "change_rev": null}, {"name": "tabular_bench.BenchmarkTabular.time_TrainTestPredictionDrift", "idx": 1, "pretty_name": "tabular_bench.BenchmarkTabular.time_TrainTestPredictionDrift('avocado')", "last_rev": 1221, "last_value": 0.17995529050000414, "last_err": 0.0, "prev_value": null, "change_rev": null}, {"name": "tabular_bench.BenchmarkTabular.time_TrainTestSamplesMix", "idx": 0, "pretty_name": "tabular_bench.BenchmarkTabular.time_TrainTestSamplesMix('lending_club')", "last_rev": 1221, "last_value": 1.3942596455000569, "last_err": 0.0, "prev_value": null, "change_rev": null}, {"name": "tabular_bench.BenchmarkTabular.time_TrainTestSamplesMix", "idx": 1, "pretty_name": "tabular_bench.BenchmarkTabular.time_TrainTestSamplesMix('avocado')", "last_rev": 1221, "last_value": 0.8378888919999952, "last_err": 0.0, "prev_value": null, "change_rev": null}, {"name": "tabular_bench.BenchmarkTabular.time_UnusedFeatures", "idx": 0, "pretty_name": "tabular_bench.BenchmarkTabular.time_UnusedFeatures('lending_club')", "last_rev": 1221, "last_value": 0.17663091899999017, "last_err": 0.0, "prev_value": null, "change_rev": null}, {"name": "tabular_bench.BenchmarkTabular.time_UnusedFeatures", "idx": 1, "pretty_name": "tabular_bench.BenchmarkTabular.time_UnusedFeatures('avocado')", "last_rev": 1221, "last_value": 0.10014001700000108, "last_err": 0.0, "prev_value": null, "change_rev": null}, {"name": "tabular_bench.BenchmarkTabular.time_WeakSegmentsPerformance", "idx": 0, "pretty_name": "tabular_bench.BenchmarkTabular.time_WeakSegmentsPerformance('lending_club')", "last_rev": 1221, "last_value": 23.716698133000023, "last_err": 0.0, "prev_value": null, "change_rev": null}, {"name": "tabular_bench.BenchmarkTabular.time_WeakSegmentsPerformance", "idx": 1, "pretty_name": "tabular_bench.BenchmarkTabular.time_WeakSegmentsPerformance('avocado')", "last_rev": 1221, "last_value": 8.520297607000032, "last_err": 0.0, "prev_value": null, "change_rev": null}, {"name": "tabular_bench.BenchmarkTabular.time_WholeDatasetDrift", "idx": 0, "pretty_name": "tabular_bench.BenchmarkTabular.time_WholeDatasetDrift('lending_club')", "last_rev": 1221, "last_value": 0.7677856530000042, "last_err": 0.0, "prev_value": null, "change_rev": null}, {"name": "tabular_bench.BenchmarkTabular.time_WholeDatasetDrift", "idx": 1, "pretty_name": "tabular_bench.BenchmarkTabular.time_WholeDatasetDrift('avocado')", "last_rev": 1221, "last_value": 0.34070877150000456, "last_err": 0.0, "prev_value": null, "change_rev": null}]